[
  {
    "action": "set_block",
    "block": "quartz_block",
    "amount": 3
  },
  {
    "action": "set_block",
    "block": "chiseled_quartz_block",
    "amount": 1
  },
  {
    "action": "set_block",
    "block": "quartz_pillar",
    "amount": 1
  },
  {
    "action": "set_block",
    "block": "gold_ore",
    "amount": 1
  },
  {
    "action": "set_block",
    "block": "stained_clay",
    "data": 3,
    "amount": 1
  },
  {
    "action": "set_block",
    "block": "sponge",
    "amount": 1
  },
  {
    "action": "set_block",
    "block": "red_mushroom_block",
    "amount": 1
  },
  {
    "action": "set_block",
    "block": "diamond_ore",
    "amount": 1
  },
  {
    "action": "set_block",
    "block": "mushroom_stem",
    "amount": 1
  },
  {
    "action": "set_block",
    "block": "smooth_quartz",
    "amount": 1
  },
  {
    "action": "set_block",
    "block": "honeycomb_block",
    "amount": 1
  },
  {
    "action": "set_block",
    "block": "redstone_ore",
    "amount": 2
  },
  {
    "action": "set_block",
    "block": "brown_mushroom_block",
    "amount": 1
  },
  {
    "action": "set_block",
    "block": "iron_ore",
    "amount": 2
  },
  {
    "action": "set_block",
    "block": "lapis_ore",
    "amount": 1
  },
  {
    "action": "set_block",
    "block": "bee_nest",
    "amount": 1
  },
  {
    "action": "set_block",
    "block": "beehive",
    "amount": 1
  },
  {
    "action": "set_block",
    "block": "emerald_ore",
    "amount": 1
  },
  {
    "action": "set_block",
    "block": "stained_clay",
    "data": 2,
    "amount": 1
  },
  {
    "action": "set_block",
    "block": "coal_ore",
    "amount": 2
  },
  {
    "action": "set_block",
    "block": "netherrack",
    "amount": 4
  },
  {
    "action": "set_block",
    "block": "soul_sand",
    "amount": 3
  },
  {
    "action": "set_block",
    "block": "magma_block",
    "amount": 2
  },
  {
    "action": "set_block",
    "block": "nether_wart_block",
    "amount": 1
  },
  {
    "action": "set_block",
    "block": "red_nether_bricks",
    "amount": 1
  },
  {
    "action": "set_block",
    "block": "obsidian",
    "amount": 1
  },
  {
    "action": "set_block",
    "block": "glowstone",
    "amount": 1
  },
  {
    "action": "set_block",
    "block": "nether_quartz_ore",
    "amount": 1
  },
  {
    "action": "set_block",
    "block": "nether_bricks",
    "amount": 1
  },
  {
    "action": "set_block",
    "block": "sandstone",
    "amount": 2
  },
  {
    "action": "set_block",
    "block": "sand",
    "amount": 4
  },
  {
    "action": "set_block",
    "block": "red_sand",
    "amount": 2
  },
  {
    "action": "set_block",
    "block": "red_sandstone",
    "amount": 2
  },
  {
    "action": "set_block",
    "block": "stained_clay",
    "data": 1,
    "amount": 1
  },
  {
    "action": "set_block",
    "block": "log_2",
    "data": 0,
    "amount": 1
  },
  {
    "action": "set_block",
    "block": "clay",
    "amount": 2
  },
  {
    "action": "set_block",
    "block": "hard_clay",
    "amount": 1
  },
  {
    "action": "set_block",
    "block": "dirt",
    "amount": 1
  },
  {
    "action": "set_block",
    "block": "white_concrete",
    "amount": 1
  },
  {
    "action": "set_block",
    "block": "stained_clay",
    "data": 4,
    "amount": 1
  },
  {
    "action": "set_block",
    "block": "hay_block",
    "amount": 1
  },
  {
    "action": "set_block",
    "block": "stained_clay",
    "data": 0,
    "amount": 1
  },
  {
    "action": "set_block",
    "block": "stained_clay",
    "data": 14,
    "amount": 1
  },
  {
    "action": "set_block",
    "block": "stained_clay",
    "data": 12,
    "amount": 1
  },
  {
    "action": "set_block",
    "block": "cobblestone",
    "amount": 3
  },
  {
    "action": "set_block",
    "block": "mossy_cobblestone",
    "amount": 3
  },
  {
    "action": "set_block",
    "block": "log",
    "data": 3,
    "amount": 1
  },
  {
    "action": "set_block",
    "block": "stone",
    "data": 1,
    "amount": 3
  },
  {
    "action": "set_block",
    "block": "stained_clay",
    "data": 13,
    "amount": 1
  },
  {
    "action": "set_block",
    "block": "stone",
    "data": 3,
    "amount": 3
  },
  {
    "action": "set_block",
    "block": "log",
    "data": 1,
    "amount": 1
  },
  {
    "action": "set_block",
    "block": "stone",
    "data": 5,
    "amount": 3
  },
  {
    "action": "set_block",
    "block": "stone",
    "amount": 7
  },
  {
    "action": "set_block",
    "block": "stained_clay",
    "data": 5,
    "amount": 1
  },
  {
    "action": "set_block",
    "block": "prismarine",
    "amount": 2
  },
  {
    "action": "set_block",
    "block": "prismarine",
    "data": 1,
    "amount": 1
  },
  {
    "action": "set_block",
    "block": "stained_clay",
    "data": 11,
    "amount": 1
  },
  {
    "action": "set_block",
    "block": "log_2",
    "data": 1,
    "amount": 1
  },
  {
    "action": "set_block",
    "block": "log",
    "data": 0,
    "amount": 1
  },
  {
    "action": "set_block",
    "block": "dried_kelp_block",
    "amount": 1
  },
  {
    "action": "set_block",
    "block": "prismarine",
    "data": 2,
    "amount": 1
  },
  {
    "action": "set_block",
    "block": "stained_clay",
    "data": 9,
    "amount": 1
  },
  {
    "action": "set_block",
    "block": "sea_lantern",
    "amount": 1
  },
  {
    "action": "set_block",
    "block": "grass",
    "nbt": "[snowy=true]",
    "amount": 2
  },
  {
    "action": "set_block",
    "block": "snow_block",
    "amount": 2
  },
  {
    "action": "set_block",
    "block": "gravel",
    "amount": 2
  },
  {
    "action": "set_block",
    "block": "packed_ice",
    "amount": 1
  },
  {
    "action": "set_block",
    "block": "sand",
    "amount": 1
  },
  {
    "action": "set_block",
    "block": "stained_clay",
    "data": 7,
    "amount": 1
  },
  {
    "action": "set_block",
    "block": "log",
    "data": 1,
    "amount": 1
  },
  {
    "action": "set_block",
    "block": "grass",
    "amount": 6
  },
  {
    "action": "set_block",
    "block": "dirt",
    "data": 2,
    "amount": 1
  }
]